setup.py
django_dont_vary_on/__init__.py
django_dont_vary_on/decorators.py
django_dont_vary_on/middleware.py
django_dont_vary_on.egg-info/PKG-INFO
django_dont_vary_on.egg-info/SOURCES.txt
django_dont_vary_on.egg-info/dependency_links.txt
django_dont_vary_on.egg-info/requires.txt
django_dont_vary_on.egg-info/top_level.txt