Metadata-Version: 1.0
Name: django-dont-vary-on
Version: 0.1.1
Summary: Library for Django to give you more control over Django's caching, and improving you cache hits and performance
Home-page: UNKNOWN
Author: Rory McCann
Author-email: rory@technomancy.org
License: GPLv3
Platform: UNKNOWN
